YTipJ.v
// Structural Function: 2x4 positive output, negative enable decoder
// Boolean Function: F = (AB' + A'B)(C + D')
// Simplified SOP: Σm(4,6,7,8,10,11)
// Dataflow Modeling (Structural)

`timescale 1ns/1ps

// 2x4 positive output, negative enable decoder
module dec2x4 (EN, in, out);
      input [1:0] in;
      input EN;
      output reg [0:3] out;
      
      always@*
            begin
                  case({EN, in})
                        3'b000: out = 4'b1000;
                        3'b001: out = 4'b0100;
                        3'b010: out = 4'b0010;
                        3'b011: out = 4'b0001;
                        default: out = 4'b0000;
                  endcase
            end

endmodule

module main(F, A, B, C, D);
      input A, B, C, D;
      output F;

      // main decoder
      wire [0:3] w;
      dec2x4 G1(~1'b1, {A, B}, w); // (EN, in, out)

      // decoder 1
      wire [0:3] d1;
      dec2x4 G2(~w[0], {C, D}, d1); // (EN, in, out)

      // decoder 2
      wire [0:3] d2;
      dec2x4 G3(~w[1], {C, D}, d2); // (EN, in, out)

      // decoder 3
      wire [0:3] d3;
      dec2x4 G4(~w[2], {C, D}, d3); // (EN, in, out)

      // decoder 4
      wire [0:3] d4;
      dec2x4 G5(~w[3], {C, D}, d4); // (EN, in, out)

      // Simplified SOP: Σm(4,6,7,8,10,11)
      assign F = d2[0] | d2[2] | d2[3] | d3[0] | d3[2] | d3[3];


endmodule

YTipJ_tb.v
// Structural Function: 2x4 positive output, negative enable decoder
// Boolean Function: F = (AB' + A'B)(C + D')
// Dataflow Modeling (Structural)

`timescale 1ns/1ps

module struct_tb();
    wire t_F;
    reg [3:0] t_input;
    integer i;

    main dut (t_F,t_input[3],t_input[2],t_input[1],t_input[0]);
    
    initial
        begin
            t_input = 4'b0000;
            for (i = 1; i < 16; i++)
                #50 t_input = i;
        end

    initial
        begin
            $display("Structural Function: 2x4 positive output, negative enable decoder");
            $display("Boolean Function: F = (AB' + A'B)(C + D')");
            $display("Dataflow Modeling (Structural)");
            $monitor("Time = %03d, ABCD = %b, F = %b", $time, t_input, t_F);
            $dumpfile("YTipJ.vcd");
            $dumpvars();
        end
endmodule

YTipJ.vcd
$date
	Tue Jul 25 13:41:14 2023
$end
$version
	Icarus Verilog
$end
$timescale
	1ps
$end
$scope module struct_tb $end
$var wire 1 ! t_F $end
$var reg 4 " t_input [3:0] $end
$var integer 32 # i [31:0] $end
$scope module dut $end
$var wire 1 $ A $end
$var wire 1 % B $end
$var wire 1 & C $end
$var wire 1 ' D $end
$var wire 1 ! F $end
$var wire 4 ( w [0:3] $end
$var wire 4 ) d4 [0:3] $end
$var wire 4 * d3 [0:3] $end
$var wire 4 + d2 [0:3] $end
$var wire 4 , d1 [0:3] $end
$scope module G1 $end
$var wire 1 - EN $end
$var wire 2 . in [1:0] $end
$var reg 4 / out [0:3] $end
$upscope $end
$scope module G2 $end
$var wire 1 0 EN $end
$var wire 2 1 in [1:0] $end
$var reg 4 2 out [0:3] $end
$upscope $end
$scope module G3 $end
$var wire 1 3 EN $end
$var wire 2 4 in [1:0] $end
$var reg 4 5 out [0:3] $end
$upscope $end
$scope module G4 $end
$var wire 1 6 EN $end
$var wire 2 7 in [1:0] $end
$var reg 4 8 out [0:3] $end
$upscope $end
$scope module G5 $end
$var wire 1 9 EN $end
$var wire 2 : in [1:0] $end
$var reg 4 ; out [0:3] $end
$upscope $end
$upscope $end
$upscope $end
$enddefinitions $end
$comment Show the parameter values. $end
$dumpall
$end
#0
$dumpvars
b0 ;
b0 :
19
b0 8
b0 7
16
b0 5
b0 4
13
b1000 2
b0 1
00
b1000 /
b0 .
0-
b1000 ,
b0 +
b0 *
b0 )
b1000 (
0'
0&
0%
0$
b1 #
b0 "
0!
$end
#50000
b100 ,
b100 2
b1 1
b1 4
b1 7
b1 :
1'
b10 #
b1 "
#100000
b10 ,
b10 2
1&
b10 1
b10 4
b10 7
b10 :
0'
b11 #
b10 "
#150000
b1 ,
b1 2
b11 1
b11 4
b11 7
b11 :
1'
b100 #
b11 "
#200000
1!
b1000 +
b1000 5
03
10
b100 (
b100 /
b0 ,
b0 2
b1 .
1%
0&
b0 1
b0 4
b0 7
b0 :
0'
b101 #
b100 "
#250000
0!
b100 +
b100 5
b1 1
b1 4
b1 7
b1 :
1'
b110 #
b101 "
#300000
1!
b10 +
b10 5
1&
b10 1
b10 4
b10 7
b10 :
0'
b111 #
b110 "
#350000
b1 +
b1 5
b11 1
b11 4
b11 7
b11 :
1'
b1000 #
b111 "
#400000
b1000 *
b1000 8
06
13
b10 (
b10 /
b0 +
b0 5
1$
b10 .
0%
0&
b0 1
b0 4
b0 7
b0 :
0'
b1001 #
b1000 "
#450000
0!
b100 *
b100 8
b1 1
b1 4
b1 7
b1 :
1'
b1010 #
b1001 "
#500000
1!
b10 *
b10 8
1&
b10 1
b10 4
b10 7
b10 :
0'
b1011 #
b1010 "
#550000
b1 *
b1 8
b11 1
b11 4
b11 7
b11 :
1'
b1100 #
b1011 "
#600000
b1000 )
b1000 ;
09
16
0!
b1 (
b1 /
b0 *
b0 8
b11 .
1%
0&
b0 1
b0 4
b0 7
b0 :
0'
b1101 #
b1100 "
#650000
b100 )
b100 ;
b1 1
b1 4
b1 7
b1 :
1'
b1110 #
b1101 "
#700000
b10 )
b10 ;
1&
b10 1
b10 4
b10 7
b10 :
0'
b1111 #
b1110 "
#750000
b1 )
b1 ;
b11 1
b11 4
b11 7
b11 :
1'
b10000 #
b1111 "
